flax_extra/__init__.py
flax_extra/batch.py
flax_extra/console.py
flax_extra/py.typed
flax_extra/random.py
flax_extra/util.py
flax_extra/version.py
flax_extra/checkpoint/__init__.py
flax_extra/checkpoint/_best_checkpoint_file_reader.py
flax_extra/checkpoint/_best_checkpoint_file_writer.py
flax_extra/checkpoint/_checkpoint.py
flax_extra/checkpoint/_checkpoint_file.py
flax_extra/checkpoint/_checkpoint_file_reader.py
flax_extra/checkpoint/_checkpoint_file_writer.py
flax_extra/checkpoint/_summary.py
flax_extra/checkpoint/_summary_logger.py
flax_extra/checkpoint/_summary_writer.py
flax_extra/combinator/__init__.py
flax_extra/combinator/_concatenate.py
flax_extra/data/__init__.py
flax_extra/data/_bytes_tokenizer.py
flax_extra/evaluation/__init__.py
flax_extra/evaluation/_loop.py
flax_extra/layer/__init__.py
flax_extra/layer/_attention.py
flax_extra/layer/_decoding.py
flax_extra/layer/_embedding_decoding.py
flax_extra/layer/_encoding.py
flax_extra/layer/_feedforward.py
flax_extra/layer/_fourier_positional_encoding.py
flax_extra/layer/_lstm.py
flax_extra/layer/_multimodal_decoding.py
flax_extra/layer/_multimodal_encoding.py
flax_extra/layer/_multimodal_positional_encoding.py
flax_extra/layer/_trainable_positional_encoding.py
flax_extra/layer/_trainable_positional_masking.py
flax_extra/layer/_trainable_positional_padding.py
flax_extra/layer/io.py
flax_extra/model/__init__.py
flax_extra/model/perceiver/__init__.py
flax_extra/model/perceiver/_cross_attention_block.py
flax_extra/model/perceiver/_decoder.py
flax_extra/model/perceiver/_encoder.py
flax_extra/model/perceiver/_io.py
flax_extra/model/perceiver/_processor.py
flax_extra/model/perceiver/_self_attention_block.py
flax_extra/model/rnn/__init__.py
flax_extra/model/rnn/_lm.py
flax_extra/operator/__init__.py
flax_extra/operator/_rearrange.py
flax_extra/operator/_reshape.py
flax_extra/operator/_shift_right.py
flax_extra/training/__init__.py
flax_extra/training/_loop.py
flax_extra-0.0.2.dist-info/LICENSE
flax_extra-0.0.2.dist-info/METADATA
flax_extra-0.0.2.dist-info/WHEEL
flax_extra-0.0.2.dist-info/top_level.txt
flax_extra-0.0.2.dist-info/RECORD
