Metadata-Version: 2.1
Name: flax-extra
Version: 0.0.2
Summary: The package provides extra flexibility to Flax using ideas originated at Trax
Home-page: https://github.com/manifest/flax-extra
Author: Andrei Nesterov
Author-email: ae.nesterov@gmail.com
License: UNKNOWN
Project-URL: Documentation, https://flax-extra.readthedocs.io
Project-URL: Source Code, https://github.com/manifest/flax-extra
Platform: UNKNOWN
Classifier: Development Status :: 3 - Alpha
Classifier: Intended Audience :: Developers
Classifier: Intended Audience :: Science/Research
Classifier: License :: OSI Approved :: Apache Software License
Classifier: Operating System :: OS Independent
Classifier: Programming Language :: Python :: 3.9
Classifier: Topic :: Scientific/Engineering :: Artificial Intelligence
Classifier: Typing :: Typed
Requires-Python: >=3.9
License-File: LICENSE
Requires-Dist: redex (>=0.1)
Requires-Dist: flax (>=0.3)
Requires-Dist: einops (>=0.3)
Requires-Dist: tensorflow (>=2.6)
Provides-Extra: development
Requires-Dist: numpy ; extra == 'development'
Requires-Dist: pylint (==2.10) ; extra == 'development'
Provides-Extra: docs
Requires-Dist: sphinx ; extra == 'docs'
Requires-Dist: furo ; extra == 'docs'
Requires-Dist: nbsphinx ; extra == 'docs'
Requires-Dist: ipykernel ; extra == 'docs'
